setup.py
flocs/__init__.py
flocs/_version.py
flocs/action_factory.py
flocs/actions.py
flocs/common.py
flocs/context.py
flocs/entities.py
flocs/entity_map.py
flocs/export.py
flocs/extractors.py
flocs/level.py
flocs/recommendation.py
flocs/reducers.py
flocs/state.py
flocs/store.py
flocs/student.py
flocs/task.py
flocs/task_session.py
flocs.egg-info/PKG-INFO
flocs.egg-info/SOURCES.txt
flocs.egg-info/dependency_links.txt
flocs.egg-info/requires.txt
flocs.egg-info/top_level.txt
flocs/data/__init__.py
flocs/data/blocks.py
flocs/data/categories.py
flocs/data/instructions.py
flocs/data/levels.py
flocs/data/tasks.py
flocs/data/toolboxes.py
flocs/tests/__init__.py
flocs/tests/fixtures_entities.py
flocs/tests/fixtures_states.py
flocs/tests/test_actions.py
flocs/tests/test_common.py
flocs/tests/test_context.py
flocs/tests/test_entities.py
flocs/tests/test_entity_map.py
flocs/tests/test_extractors.py
flocs/tests/test_level.py
flocs/tests/test_recommendation.py
flocs/tests/test_reducers.py
flocs/tests/test_state.py
flocs/tests/test_store.py
flocs/tests/test_student.py
flocs/tests/test_task.py
flocs/tests/test_task_session.py
flocs/utils/__init__.py
flocs/utils/names.py