Metadata-Version: 1.0
Name: flocs
Version: 0.0.16
Summary: Components for adaptive learning of computer science
Home-page: https://github.com/adaptive-learning/flocs-core
Author: Tomas Effenberger
Author-email: tomas.effenberger@gmail.com
License: MIT
Platform: UNKNOWN
